README.md
setup.cfg
setup.py
service_firemap_python/__init__.py
service_firemap_python.egg-info/PKG-INFO
service_firemap_python.egg-info/SOURCES.txt
service_firemap_python.egg-info/dependency_links.txt
service_firemap_python.egg-info/requires.txt
service_firemap_python.egg-info/top_level.txt
service_firemap_python.egg-info/zip-safe
service_firemap_python/build/FireMapServiceFactory.py
service_firemap_python/build/__init__.py
service_firemap_python/container/FireMapProcess.py
service_firemap_python/container/__init__.py
service_firemap_python/data/__init__.py
service_firemap_python/data/version1/FireMapTileBlockV1.py
service_firemap_python/data/version1/FireMapTileV1.py
service_firemap_python/data/version1/FireMapUpdateTypeV1.py
service_firemap_python/data/version1/FireMapUpdateV1.py
service_firemap_python/data/version1/FireMapUpdateV1Schema.py
service_firemap_python/data/version1/FireMapZoomV1.py
service_firemap_python/data/version1/LocationV1.py
service_firemap_python/data/version1/__init__.py
service_firemap_python/logic/FireMapCommandSet.py
service_firemap_python/logic/FireMapController.py
service_firemap_python/logic/IFireMapController.py
service_firemap_python/logic/__init__.py
service_firemap_python/map_utils/FireMapUtil.py
service_firemap_python/map_utils/__init__.py
service_firemap_python/persistence/FireMapFilePersistence.py
service_firemap_python/persistence/FireMapMemoryPersistence.py
service_firemap_python/persistence/FireMapMongoDbPersistence.py
service_firemap_python/persistence/IFireMapPersistence.py
service_firemap_python/persistence/__init__.py
service_firemap_python/services/__init__.py
service_firemap_python/services/version1/FireMapsCommandableHttpServiceV1.py
service_firemap_python/services/version1/__init__.py
test/logic/__init__.py
test/logic/test_FireMapController.py
test/persistence/FireMapPersistenceFixture.py
test/persistence/__init__.py
test/persistence/test_FireMapFilePersistence.py
test/persistence/test_FireMapMemoryPersistence.py
test/persistence/test_FireMapMongoDbPersistence.py
test/services/__init__.py
test/services/version1/__init__.py
test/services/version1/test_FireMapHttpService.py