Metadata-Version: 2.1
Name: service-firemap-python
Version: 1.0.2
Summary: FireMap data microservice in Python
Home-page: https://gitlab.com/eic-stopfires/service-firemap-python
Author: Conceptual Vision Consulting LLC
License: UNKNOWN
Platform: any
Classifier: Operating System :: OS Independent
Classifier: Programming Language :: Python
Classifier: Programming Language :: Python :: 3.6
Classifier: Programming Language :: Python :: 3.7
Classifier: Programming Language :: Python :: 3.8
Classifier: Programming Language :: Python :: 3.9
